cellium/__init__.py
cellium/client.py
cellium-0.1.0.dist-info/LICENSE
cellium-0.1.0.dist-info/METADATA
cellium-0.1.0.dist-info/WHEEL
cellium-0.1.0.dist-info/RECORD
