Metadata-Version: 2.1
Name: cellium
Version: 0.1.0
Summary: Inference client for the Cellium Network. Created by Agent Artificial. Based on OpenAI's API Client.
Author: Richard Porteous
Author-email: richard@agentartificial.com
Requires-Python: >=3.10,<4.0
Classifier: License :: OSI Approved :: MIT License
Classifier: Operating System :: OS Independent
Classifier: Programming Language :: Python :: 3
Classifier: Programming Language :: Python :: 3.10
Classifier: Programming Language :: Python :: 3.11
Classifier: Programming Language :: Python :: 3.12
Requires-Dist: httpx (>=0.27.0,<0.28.0)
Requires-Dist: loguru (>=0.7.2,<0.8.0)
Requires-Dist: openai (>=1.14.2,<2.0.0)
Requires-Dist: python-dotenv (>=1.0.1,<2.0.0)
Requires-Dist: websocket (>=0.2.1,<0.3.0)
